{
  "daily": [
    {
      "date": "2025-09-26",
      "kimbap": 0,
      "commits": 0,
      "worked": 2,
      "cultural": 4,
      "steps": 4000,
      "tags": 0,
      "draft": 0,
      "coordinates": 0,
      "lat": 0,
      "lng": 0,
      "work": 0
    },
    {
      "date": "2025-09-27",
      "kimbap": 0,
      "commits": 0,
      "worked": 2,
      "cultural": 3,
      "steps": 5000,
      "tags": 0,
      "draft": 0,
      "coordinates": 0,
      "lat": 0,
      "lng": 0,
      "work": 0
    },
    {
      "date": "2025-09-28",
      "kimbap": 1,
      "commits": 0,
      "worked": 1,
      "cultural": 0,
      "steps": 7000,
      "tags": 0,
      "draft": 0,
      "coordinates": 0,
      "lat": 0,
      "lng": 0,
      "work": 0
    },
    {
      "date": "2025-09-29",
      "kimbap": 2,
      "commits": 0,
      "worked": 0,
      "cultural": 5,
      "steps": 7000,
      "tags": 0,
      "draft": 0,
      "coordinates": 0,
      "lat": 0,
      "lng": 0,
      "work": 0
    },
    {
      "date": "2025-09-30",
      "kimbap": 0,
      "commits": 0,
      "worked": 0,
      "cultural": 1,
      "steps": 0,
      "tags": 0,
      "draft": 0,
      "coordinates": 0,
      "lat": 0,
      "lng": 0,
      "work": 0
    },
    {
      "date": "2025-10-01",
      "kimbap": 0,
      "commits": 0,
      "worked": 3,
      "cultural": 1,
      "steps": 6000,
      "tags": 0,
      "draft": 0,
      "coordinates": 0,
      "lat": 0,
      "lng": 0,
      "work": 0
    },
    {
      "date": "2025-10-02",
      "kimbap": 0,
      "commits": 0,
      "worked": 2,
      "cultural": 5,
      "steps": 3000,
      "tags": 0,
      "draft": 0,
      "coordinates": 0,
      "lat": 0,
      "lng": 0,
      "work": 0
    },
    {
      "date": "2025-10-03",
      "kimbap": 0,
      "commits": 0,
      "worked": 0,
      "cultural": 7,
      "steps": 5000,
      "tags": 0,
      "draft": 0,
      "coordinates": 0,
      "lat": 0,
      "lng": 0,
      "work": 0
    },
    {
      "date": "2025-10-04",
      "kimbap": 2,
      "commits": 0,
      "worked": 3,
      "cultural": 0,
      "steps": 5000,
      "tags": 0,
      "draft": 0,
      "coordinates": 0,
      "lat": 0,
      "lng": 0,
      "work": 0
    },
    {
      "date": "2025-10-05",
      "kimbap": 2,
      "commits": 0,
      "worked": 3,
      "cultural": 4,
      "steps": 2000,
      "tags": 0,
      "draft": 0,
      "coordinates": 0,
      "lat": 0,
      "lng": 0,
      "work": 0
    },
    {
      "date": "2025-10-06",
      "kimbap": 0,
      "commits": 0,
      "worked": 3,
      "cultural": 4,
      "steps": 4000,
      "tags": 0,
      "draft": 0,
      "coordinates": 0,
      "lat": 0,
      "lng": 0,
      "work": 0
    },
    {
      "date": "2025-10-07",
      "kimbap": 0,
      "commits": 0,
      "worked": 2,
      "cultural": 6,
      "steps": 3000,
      "tags": 0,
      "draft": 0,
      "coordinates": 0,
      "lat": 0,
      "lng": 0,
      "work": 0
    },
    {
      "date": "2025-10-08",
      "kimbap": 2,
      "commits": 0,
      "worked": 1,
      "cultural": 7,
      "steps": 5000,
      "tags": 0,
      "draft": 0,
      "coordinates": 0,
      "lat": 0,
      "lng": 0,
      "work": 0
    },
    {
      "date": "2025-10-09",
      "kimbap": 0,
      "commits": 0,
      "worked": 4,
      "cultural": 7,
      "steps": 3000,
      "tags": 0,
      "draft": 0,
      "coordinates": 0,
      "lat": 0,
      "lng": 0,
      "work": 0
    },
    {
      "date": "2025-10-10",
      "kimbap": 0,
      "commits": 0,
      "worked": 4,
      "cultural": 5,
      "steps": 1000,
      "tags": 0,
      "draft": 0,
      "coordinates": 0,
      "lat": 0,
      "lng": 0,
      "work": 0
    },
    {
      "date": "2025-10-11",
      "kimbap": 1,
      "commits": 0,
      "worked": 3,
      "cultural": 0,
      "steps": 0,
      "tags": 0,
      "draft": 0,
      "coordinates": 0,
      "lat": 0,
      "lng": 0,
      "work": 0
    },
    {
      "date": "2025-10-12",
      "kimbap": 2,
      "commits": 0,
      "worked": 2,
      "cultural": 0,
      "steps": 3000,
      "tags": 0,
      "draft": 0,
      "coordinates": 0,
      "lat": 0,
      "lng": 0,
      "work": 0
    },
    {
      "date": "2025-10-13",
      "kimbap": 0,
      "commits": 0,
      "worked": 2,
      "cultural": 5,
      "steps": 9000,
      "tags": 0,
      "draft": 0,
      "coordinates": 0,
      "lat": 0,
      "lng": 0,
      "work": 0
    },
    {
      "date": "2025-10-14",
      "kimbap": 0,
      "commits": 0,
      "worked": 0,
      "cultural": 5,
      "steps": 6000,
      "tags": 0,
      "draft": 0,
      "coordinates": 0,
      "lat": 0,
      "lng": 0,
      "work": 0
    },
    {
      "date": "2025-10-15",
      "kimbap": 1,
      "commits": 0,
      "worked": 2,
      "cultural": 0,
      "steps": 3000,
      "tags": 0,
      "draft": 0,
      "coordinates": 0,
      "lat": 0,
      "lng": 0,
      "work": 0
    },
    {
      "date": "2025-10-16",
      "kimbap": 0,
      "commits": 0,
      "worked": 0,
      "cultural": 4,
      "steps": 2000,
      "tags": 0,
      "draft": 0,
      "coordinates": 0,
      "lat": 0,
      "lng": 0,
      "work": 0
    },
    {
      "date": "2025-10-17",
      "kimbap": 0,
      "commits": 0,
      "worked": 0,
      "cultural": 4,
      "steps": 1000,
      "tags": 0,
      "draft": 0,
      "coordinates": 0,
      "lat": 0,
      "lng": 0,
      "work": 0
    },
    {
      "date": "2025-10-18",
      "kimbap": 2,
      "commits": 0,
      "worked": 1,
      "cultural": 7,
      "steps": 9000,
      "tags": 0,
      "draft": 0,
      "coordinates": 0,
      "lat": 0,
      "lng": 0,
      "work": 0
    },
    {
      "date": "2025-10-19",
      "kimbap": 2,
      "commits": 0,
      "worked": 3,
      "cultural": 1,
      "steps": 9000,
      "tags": 0,
      "draft": 0,
      "coordinates": 0,
      "lat": 0,
      "lng": 0,
      "work": 0
    },
    {
      "date": "2025-10-20",
      "kimbap": 0,
      "commits": 0,
      "worked": 1,
      "cultural": 5,
      "steps": 0,
      "tags": 0,
      "draft": 0,
      "coordinates": 0,
      "lat": 0,
      "lng": 0,
      "work": 0
    },
    {
      "date": "2025-10-21",
      "kimbap": 2,
      "commits": 0,
      "worked": 3,
      "cultural": 2,
      "steps": 7000,
      "tags": 0,
      "draft": 0,
      "coordinates": 0,
      "lat": 0,
      "lng": 0,
      "work": 0
    },
    {
      "date": "2025-10-22",
      "kimbap": 1,
      "commits": 0,
      "worked": 4,
      "cultural": 7,
      "steps": 6000,
      "tags": 0,
      "draft": 0,
      "coordinates": 0,
      "lat": 0,
      "lng": 0,
      "work": 0
    },
    {
      "date": "2025-10-23",
      "kimbap": 2,
      "commits": 0,
      "worked": 4,
      "cultural": 0,
      "steps": 9000,
      "tags": 0,
      "draft": 0,
      "coordinates": 0,
      "lat": 0,
      "lng": 0,
      "work": 0
    },
    {
      "date": "2025-10-24",
      "kimbap": 2,
      "commits": 0,
      "worked": 4,
      "cultural": 4,
      "steps": 3000,
      "tags": 0,
      "draft": 0,
      "coordinates": 0,
      "lat": 0,
      "lng": 0,
      "work": 0
    },
    {
      "date": "2025-10-25",
      "kimbap": 2,
      "commits": 0,
      "worked": 2,
      "cultural": 2,
      "steps": 8000,
      "tags": 0,
      "draft": 0,
      "coordinates": 0,
      "lat": 0,
      "lng": 0,
      "work": 0
    },
    {
      "date": "2025-10-26",
      "kimbap": 1,
      "commits": 0,
      "worked": 2,
      "cultural": 3,
      "steps": 9000,
      "tags": 0,
      "draft": 0,
      "coordinates": 0,
      "lat": 0,
      "lng": 0,
      "work": 0
    },
    {
      "date": "2025-10-27",
      "kimbap": 0,
      "commits": 0,
      "worked": 3,
      "cultural": 3,
      "steps": 7000,
      "tags": 0,
      "draft": 0,
      "coordinates": 0,
      "lat": 0,
      "lng": 0,
      "work": 0
    },
    {
      "date": "2025-10-28",
      "kimbap": 1,
      "commits": 0,
      "worked": 1,
      "cultural": 1,
      "steps": 0,
      "tags": 0,
      "draft": 0,
      "coordinates": 0,
      "lat": 0,
      "lng": 0,
      "work": 0
    },
    {
      "date": "2025-10-29",
      "kimbap": 1,
      "commits": 0,
      "worked": 3,
      "cultural": 2,
      "steps": 6000,
      "tags": 0,
      "draft": 0,
      "coordinates": 0,
      "lat": 0,
      "lng": 0,
      "work": 0
    },
    {
      "date": "2025-10-30",
      "kimbap": 0,
      "commits": 0,
      "worked": 3,
      "cultural": 5,
      "steps": 4000,
      "tags": 0,
      "draft": 0,
      "coordinates": 0,
      "lat": 0,
      "lng": 0,
      "work": 0
    },
    {
      "date": "2025-10-31",
      "kimbap": 2,
      "commits": 0,
      "worked": 4,
      "cultural": 7,
      "steps": 2000,
      "tags": 0,
      "draft": 0,
      "coordinates": 0,
      "lat": 0,
      "lng": 0,
      "work": 0
    },
    {
      "date": "2025-11-01",
      "kimbap": 0,
      "commits": 0,
      "worked": 4,
      "cultural": 7,
      "steps": 5000,
      "tags": 0,
      "draft": 0,
      "coordinates": 0,
      "lat": 0,
      "lng": 0,
      "work": 0
    },
    {
      "date": "2025-11-02",
      "kimbap": 1,
      "commits": 0,
      "worked": 0,
      "cultural": 3,
      "steps": 1000,
      "tags": 0,
      "draft": 0,
      "coordinates": 0,
      "lat": 0,
      "lng": 0,
      "work": 0
    },
    {
      "date": "2025-11-03",
      "kimbap": 2,
      "commits": 0,
      "worked": 1,
      "cultural": 0,
      "steps": 7000,
      "tags": 0,
      "draft": 0,
      "coordinates": 0,
      "lat": 0,
      "lng": 0,
      "work": 0
    },
    {
      "date": "2025-11-04",
      "kimbap": 1,
      "commits": 0,
      "worked": 2,
      "cultural": 6,
      "steps": 9000,
      "tags": 0,
      "draft": 0,
      "coordinates": 0,
      "lat": 0,
      "lng": 0,
      "work": 0
    },
    {
      "date": "2025-11-05",
      "kimbap": 0,
      "commits": 0,
      "worked": 3,
      "cultural": 1,
      "steps": 0,
      "tags": 0,
      "draft": 0,
      "coordinates": 0,
      "lat": 0,
      "lng": 0,
      "work": 0
    },
    {
      "date": "2025-11-06",
      "kimbap": 2,
      "commits": 0,
      "worked": 3,
      "cultural": 7,
      "steps": 5000,
      "tags": 0,
      "draft": 0,
      "coordinates": 0,
      "lat": 0,
      "lng": 0,
      "work": 0
    },
    {
      "date": "2025-11-07",
      "kimbap": 0,
      "commits": 0,
      "worked": 4,
      "cultural": 1,
      "steps": 5000,
      "tags": 0,
      "draft": 0,
      "coordinates": 0,
      "lat": 0,
      "lng": 0,
      "work": 0
    },
    {
      "date": "2025-11-08",
      "kimbap": 2,
      "commits": 0,
      "worked": 1,
      "cultural": 6,
      "steps": 1000,
      "tags": 0,
      "draft": 0,
      "coordinates": 0,
      "lat": 0,
      "lng": 0,
      "work": 0
    },
    {
      "date": "2025-11-09",
      "kimbap": 2,
      "commits": 0,
      "worked": 0,
      "cultural": 5,
      "steps": 5000,
      "tags": 0,
      "draft": 0,
      "coordinates": 0,
      "lat": 0,
      "lng": 0,
      "work": 0
    },
    {
      "date": "2025-11-10",
      "kimbap": 0,
      "commits": 0,
      "worked": 2,
      "cultural": 5,
      "steps": 9000,
      "tags": 0,
      "draft": 0,
      "coordinates": 0,
      "lat": 0,
      "lng": 0,
      "work": 0
    },
    {
      "date": "2025-11-11",
      "kimbap": 1,
      "commits": 0,
      "worked": 1,
      "cultural": 4,
      "steps": 7000,
      "tags": 0,
      "draft": 0,
      "coordinates": 0,
      "lat": 0,
      "lng": 0,
      "work": 0
    },
    {
      "date": "2025-11-12",
      "kimbap": 1,
      "commits": 0,
      "worked": 2,
      "cultural": 1,
      "steps": 5000,
      "tags": 0,
      "draft": 0,
      "coordinates": 0,
      "lat": 0,
      "lng": 0,
      "work": 0
    },
    {
      "date": "2025-11-13",
      "kimbap": 1,
      "commits": 0,
      "worked": 0,
      "cultural": 5,
      "steps": 1000,
      "tags": 0,
      "draft": 0,
      "coordinates": 0,
      "lat": 0,
      "lng": 0,
      "work": 0
    },
    {
      "date": "2025-11-14",
      "kimbap": 0,
      "commits": 0,
      "worked": 3,
      "cultural": 3,
      "steps": 5000,
      "tags": 0,
      "draft": 0,
      "coordinates": 0,
      "lat": 0,
      "lng": 0,
      "work": 0
    },
    {
      "date": "2025-11-15",
      "kimbap": 0,
      "commits": 0,
      "worked": 0,
      "cultural": 5,
      "steps": 2000,
      "tags": 0,
      "draft": 0,
      "coordinates": 0,
      "lat": 0,
      "lng": 0,
      "work": 0
    },
    {
      "date": "2025-11-16",
      "kimbap": 2,
      "commits": 0,
      "worked": 1,
      "cultural": 1,
      "steps": 6000,
      "tags": 0,
      "draft": 0,
      "coordinates": 0,
      "lat": 0,
      "lng": 0,
      "work": 0
    },
    {
      "date": "2025-11-17",
      "kimbap": 2,
      "commits": 0,
      "worked": 3,
      "cultural": 3,
      "steps": 8000,
      "tags": 0,
      "draft": 0,
      "coordinates": 0,
      "lat": 0,
      "lng": 0,
      "work": 0
    },
    {
      "date": "2025-11-18",
      "kimbap": 2,
      "commits": 0,
      "worked": 3,
      "cultural": 7,
      "steps": 3000,
      "tags": 0,
      "draft": 0,
      "coordinates": 0,
      "lat": 0,
      "lng": 0,
      "work": 0
    },
    {
      "date": "2025-11-19",
      "kimbap": 1,
      "commits": 0,
      "worked": 1,
      "cultural": 5,
      "steps": 2000,
      "tags": 0,
      "draft": 0,
      "coordinates": 0,
      "lat": 0,
      "lng": 0,
      "work": 0
    },
    {
      "date": "2025-11-20",
      "kimbap": 2,
      "commits": 0,
      "worked": 2,
      "cultural": 1,
      "steps": 7000,
      "tags": 0,
      "draft": 0,
      "coordinates": 0,
      "lat": 0,
      "lng": 0,
      "work": 0
    },
    {
      "date": "2025-11-21",
      "kimbap": 1,
      "commits": 0,
      "worked": 0,
      "cultural": 6,
      "steps": 8000,
      "tags": 0,
      "draft": 0,
      "coordinates": 0,
      "lat": 0,
      "lng": 0,
      "work": 0
    },
    {
      "date": "2025-11-22",
      "kimbap": 0,
      "commits": 0,
      "worked": 2,
      "cultural": 4,
      "steps": 2000,
      "tags": 0,
      "draft": 0,
      "coordinates": 0,
      "lat": 0,
      "lng": 0,
      "work": 0
    },
    {
      "date": "2025-11-23",
      "kimbap": 0,
      "commits": 0,
      "worked": 4,
      "cultural": 1,
      "steps": 3000,
      "tags": 0,
      "draft": 0,
      "coordinates": 0,
      "lat": 0,
      "lng": 0,
      "work": 0
    },
    {
      "date": "2025-11-24",
      "kimbap": 1,
      "commits": 0,
      "worked": 3,
      "cultural": 4,
      "steps": 4000,
      "tags": 0,
      "draft": 0,
      "coordinates": 0,
      "lat": 0,
      "lng": 0,
      "work": 0
    },
    {
      "date": "2025-11-25",
      "kimbap": 2,
      "commits": 0,
      "worked": 4,
      "cultural": 4,
      "steps": 2000,
      "tags": 0,
      "draft": 0,
      "coordinates": 0,
      "lat": 0,
      "lng": 0,
      "work": 0
    },
    {
      "date": "2025-11-26",
      "kimbap": 2,
      "commits": 0,
      "worked": 0,
      "cultural": 0,
      "steps": 6000,
      "tags": 0,
      "draft": 0,
      "coordinates": 0,
      "lat": 0,
      "lng": 0,
      "work": 0
    },
    {
      "date": "2025-11-27",
      "kimbap": 1,
      "commits": 0,
      "worked": 1,
      "cultural": 3,
      "steps": 7000,
      "tags": 0,
      "draft": 0,
      "coordinates": 0,
      "lat": 0,
      "lng": 0,
      "work": 0
    },
    {
      "date": "2025-11-28",
      "kimbap": 0,
      "commits": 0,
      "worked": 0,
      "cultural": 4,
      "steps": 9000,
      "tags": 0,
      "draft": 0,
      "coordinates": 0,
      "lat": 0,
      "lng": 0,
      "work": 0
    },
    {
      "date": "2025-11-29",
      "kimbap": 1,
      "commits": 0,
      "worked": 2,
      "cultural": 6,
      "steps": 0,
      "tags": 0,
      "draft": 0,
      "coordinates": 0,
      "lat": 0,
      "lng": 0,
      "work": 0
    },
    {
      "date": "2025-11-30",
      "kimbap": 2,
      "commits": 0,
      "worked": 2,
      "cultural": 6,
      "steps": 3000,
      "tags": 0,
      "draft": 0,
      "coordinates": 0,
      "lat": 0,
      "lng": 0,
      "work": 0
    },
    {
      "date": "2025-12-01",
      "kimbap": 1,
      "commits": 0,
      "worked": 3,
      "cultural": 0,
      "steps": 5000,
      "tags": 0,
      "draft": 0,
      "coordinates": 0,
      "lat": 0,
      "lng": 0,
      "work": 0
    },
    {
      "date": "2025-12-02",
      "kimbap": 2,
      "commits": 0,
      "worked": 1,
      "cultural": 2,
      "steps": 0,
      "tags": 0,
      "draft": 0,
      "coordinates": 0,
      "lat": 0,
      "lng": 0,
      "work": 0
    },
    {
      "date": "2025-12-03",
      "kimbap": 2,
      "commits": 0,
      "worked": 0,
      "cultural": 0,
      "steps": 1000,
      "tags": 0,
      "draft": 0,
      "coordinates": 0,
      "lat": 0,
      "lng": 0,
      "work": 0
    },
    {
      "date": "2025-12-04",
      "kimbap": 1,
      "commits": 0,
      "worked": 0,
      "cultural": 5,
      "steps": 0,
      "tags": 0,
      "draft": 0,
      "coordinates": 0,
      "lat": 0,
      "lng": 0,
      "work": 0
    }
  ],
  "cumulative": [
    {
      "date": "2025-09-26",
      "kimbap": 0,
      "commits": 0,
      "cultural": 4,
      "steps": 4,
      "worked": 2
    },
    {
      "date": "2025-09-27",
      "kimbap": 0,
      "commits": 0,
      "cultural": 7,
      "steps": 9,
      "worked": 4
    },
    {
      "date": "2025-09-28",
      "kimbap": 1,
      "commits": 0,
      "cultural": 7,
      "steps": 16,
      "worked": 5
    },
    {
      "date": "2025-09-29",
      "kimbap": 3,
      "commits": 0,
      "cultural": 12,
      "steps": 23,
      "worked": 5
    },
    {
      "date": "2025-09-30",
      "kimbap": 3,
      "commits": 0,
      "cultural": 13,
      "steps": 23,
      "worked": 5
    },
    {
      "date": "2025-10-01",
      "kimbap": 3,
      "commits": 0,
      "cultural": 14,
      "steps": 29,
      "worked": 8
    },
    {
      "date": "2025-10-02",
      "kimbap": 3,
      "commits": 0,
      "cultural": 19,
      "steps": 32,
      "worked": 10
    },
    {
      "date": "2025-10-03",
      "kimbap": 3,
      "commits": 0,
      "cultural": 26,
      "steps": 37,
      "worked": 10
    },
    {
      "date": "2025-10-04",
      "kimbap": 5,
      "commits": 0,
      "cultural": 26,
      "steps": 42,
      "worked": 13
    },
    {
      "date": "2025-10-05",
      "kimbap": 7,
      "commits": 0,
      "cultural": 30,
      "steps": 44,
      "worked": 16
    },
    {
      "date": "2025-10-06",
      "kimbap": 7,
      "commits": 0,
      "cultural": 34,
      "steps": 48,
      "worked": 19
    },
    {
      "date": "2025-10-07",
      "kimbap": 7,
      "commits": 0,
      "cultural": 40,
      "steps": 51,
      "worked": 21
    },
    {
      "date": "2025-10-08",
      "kimbap": 9,
      "commits": 0,
      "cultural": 47,
      "steps": 56,
      "worked": 22
    },
    {
      "date": "2025-10-09",
      "kimbap": 9,
      "commits": 0,
      "cultural": 54,
      "steps": 59,
      "worked": 26
    },
    {
      "date": "2025-10-10",
      "kimbap": 9,
      "commits": 0,
      "cultural": 59,
      "steps": 60,
      "worked": 30
    },
    {
      "date": "2025-10-11",
      "kimbap": 10,
      "commits": 0,
      "cultural": 59,
      "steps": 60,
      "worked": 33
    },
    {
      "date": "2025-10-12",
      "kimbap": 12,
      "commits": 0,
      "cultural": 59,
      "steps": 63,
      "worked": 35
    },
    {
      "date": "2025-10-13",
      "kimbap": 12,
      "commits": 0,
      "cultural": 64,
      "steps": 72,
      "worked": 37
    },
    {
      "date": "2025-10-14",
      "kimbap": 12,
      "commits": 0,
      "cultural": 69,
      "steps": 78,
      "worked": 37
    },
    {
      "date": "2025-10-15",
      "kimbap": 13,
      "commits": 0,
      "cultural": 69,
      "steps": 81,
      "worked": 39
    },
    {
      "date": "2025-10-16",
      "kimbap": 13,
      "commits": 0,
      "cultural": 73,
      "steps": 83,
      "worked": 39
    },
    {
      "date": "2025-10-17",
      "kimbap": 13,
      "commits": 0,
      "cultural": 77,
      "steps": 84,
      "worked": 39
    },
    {
      "date": "2025-10-18",
      "kimbap": 15,
      "commits": 0,
      "cultural": 84,
      "steps": 93,
      "worked": 40
    },
    {
      "date": "2025-10-19",
      "kimbap": 17,
      "commits": 0,
      "cultural": 85,
      "steps": 102,
      "worked": 43
    },
    {
      "date": "2025-10-20",
      "kimbap": 17,
      "commits": 0,
      "cultural": 90,
      "steps": 102,
      "worked": 44
    },
    {
      "date": "2025-10-21",
      "kimbap": 19,
      "commits": 0,
      "cultural": 92,
      "steps": 109,
      "worked": 47
    },
    {
      "date": "2025-10-22",
      "kimbap": 20,
      "commits": 0,
      "cultural": 99,
      "steps": 115,
      "worked": 51
    },
    {
      "date": "2025-10-23",
      "kimbap": 22,
      "commits": 0,
      "cultural": 99,
      "steps": 124,
      "worked": 55
    },
    {
      "date": "2025-10-24",
      "kimbap": 24,
      "commits": 0,
      "cultural": 103,
      "steps": 127,
      "worked": 59
    },
    {
      "date": "2025-10-25",
      "kimbap": 26,
      "commits": 0,
      "cultural": 105,
      "steps": 135,
      "worked": 61
    },
    {
      "date": "2025-10-26",
      "kimbap": 27,
      "commits": 0,
      "cultural": 108,
      "steps": 144,
      "worked": 63
    },
    {
      "date": "2025-10-27",
      "kimbap": 27,
      "commits": 0,
      "cultural": 111,
      "steps": 151,
      "worked": 66
    },
    {
      "date": "2025-10-28",
      "kimbap": 28,
      "commits": 0,
      "cultural": 112,
      "steps": 151,
      "worked": 67
    },
    {
      "date": "2025-10-29",
      "kimbap": 29,
      "commits": 0,
      "cultural": 114,
      "steps": 157,
      "worked": 70
    },
    {
      "date": "2025-10-30",
      "kimbap": 29,
      "commits": 0,
      "cultural": 119,
      "steps": 161,
      "worked": 73
    },
    {
      "date": "2025-10-31",
      "kimbap": 31,
      "commits": 0,
      "cultural": 126,
      "steps": 163,
      "worked": 77
    },
    {
      "date": "2025-11-01",
      "kimbap": 31,
      "commits": 0,
      "cultural": 133,
      "steps": 168,
      "worked": 81
    },
    {
      "date": "2025-11-02",
      "kimbap": 32,
      "commits": 0,
      "cultural": 136,
      "steps": 169,
      "worked": 81
    },
    {
      "date": "2025-11-03",
      "kimbap": 34,
      "commits": 0,
      "cultural": 136,
      "steps": 176,
      "worked": 82
    },
    {
      "date": "2025-11-04",
      "kimbap": 35,
      "commits": 0,
      "cultural": 142,
      "steps": 185,
      "worked": 84
    },
    {
      "date": "2025-11-05",
      "kimbap": 35,
      "commits": 0,
      "cultural": 143,
      "steps": 185,
      "worked": 87
    },
    {
      "date": "2025-11-06",
      "kimbap": 37,
      "commits": 0,
      "cultural": 150,
      "steps": 190,
      "worked": 90
    },
    {
      "date": "2025-11-07",
      "kimbap": 37,
      "commits": 0,
      "cultural": 151,
      "steps": 195,
      "worked": 94
    },
    {
      "date": "2025-11-08",
      "kimbap": 39,
      "commits": 0,
      "cultural": 157,
      "steps": 196,
      "worked": 95
    },
    {
      "date": "2025-11-09",
      "kimbap": 41,
      "commits": 0,
      "cultural": 162,
      "steps": 201,
      "worked": 95
    },
    {
      "date": "2025-11-10",
      "kimbap": 41,
      "commits": 0,
      "cultural": 167,
      "steps": 210,
      "worked": 97
    },
    {
      "date": "2025-11-11",
      "kimbap": 42,
      "commits": 0,
      "cultural": 171,
      "steps": 217,
      "worked": 98
    },
    {
      "date": "2025-11-12",
      "kimbap": 43,
      "commits": 0,
      "cultural": 172,
      "steps": 222,
      "worked": 100
    },
    {
      "date": "2025-11-13",
      "kimbap": 44,
      "commits": 0,
      "cultural": 177,
      "steps": 223,
      "worked": 100
    },
    {
      "date": "2025-11-14",
      "kimbap": 44,
      "commits": 0,
      "cultural": 180,
      "steps": 228,
      "worked": 103
    },
    {
      "date": "2025-11-15",
      "kimbap": 44,
      "commits": 0,
      "cultural": 185,
      "steps": 230,
      "worked": 103
    },
    {
      "date": "2025-11-16",
      "kimbap": 46,
      "commits": 0,
      "cultural": 186,
      "steps": 236,
      "worked": 104
    },
    {
      "date": "2025-11-17",
      "kimbap": 48,
      "commits": 0,
      "cultural": 189,
      "steps": 244,
      "worked": 107
    },
    {
      "date": "2025-11-18",
      "kimbap": 50,
      "commits": 0,
      "cultural": 196,
      "steps": 247,
      "worked": 110
    },
    {
      "date": "2025-11-19",
      "kimbap": 51,
      "commits": 0,
      "cultural": 201,
      "steps": 249,
      "worked": 111
    },
    {
      "date": "2025-11-20",
      "kimbap": 53,
      "commits": 0,
      "cultural": 202,
      "steps": 256,
      "worked": 113
    },
    {
      "date": "2025-11-21",
      "kimbap": 54,
      "commits": 0,
      "cultural": 208,
      "steps": 264,
      "worked": 113
    },
    {
      "date": "2025-11-22",
      "kimbap": 54,
      "commits": 0,
      "cultural": 212,
      "steps": 266,
      "worked": 115
    },
    {
      "date": "2025-11-23",
      "kimbap": 54,
      "commits": 0,
      "cultural": 213,
      "steps": 269,
      "worked": 119
    },
    {
      "date": "2025-11-24",
      "kimbap": 55,
      "commits": 0,
      "cultural": 217,
      "steps": 273,
      "worked": 122
    },
    {
      "date": "2025-11-25",
      "kimbap": 57,
      "commits": 0,
      "cultural": 221,
      "steps": 275,
      "worked": 126
    },
    {
      "date": "2025-11-26",
      "kimbap": 59,
      "commits": 0,
      "cultural": 221,
      "steps": 281,
      "worked": 126
    },
    {
      "date": "2025-11-27",
      "kimbap": 60,
      "commits": 0,
      "cultural": 224,
      "steps": 288,
      "worked": 127
    },
    {
      "date": "2025-11-28",
      "kimbap": 60,
      "commits": 0,
      "cultural": 228,
      "steps": 297,
      "worked": 127
    },
    {
      "date": "2025-11-29",
      "kimbap": 61,
      "commits": 0,
      "cultural": 234,
      "steps": 297,
      "worked": 129
    },
    {
      "date": "2025-11-30",
      "kimbap": 63,
      "commits": 0,
      "cultural": 240,
      "steps": 300,
      "worked": 131
    },
    {
      "date": "2025-12-01",
      "kimbap": 64,
      "commits": 0,
      "cultural": 240,
      "steps": 305,
      "worked": 134
    },
    {
      "date": "2025-12-02",
      "kimbap": 66,
      "commits": 0,
      "cultural": 242,
      "steps": 305,
      "worked": 135
    },
    {
      "date": "2025-12-03",
      "kimbap": 68,
      "commits": 0,
      "cultural": 242,
      "steps": 306,
      "worked": 135
    },
    {
      "date": "2025-12-04",
      "kimbap": 69,
      "commits": 0,
      "cultural": 247,
      "steps": 306,
      "worked": 135
    }
  ],
  "summary": {
    "totalDays": 70,
    "dateRange": {
      "start": "2025-09-26",
      "end": "2025-12-04"
    },
    "totals": {
      "kimbap": 69,
      "commits": 0,
      "cultural": 247,
      "steps": 306000,
      "worked": 135
    },
    "averages": {
      "kimbap": "0.99",
      "commits": "0.00",
      "cultural": "3.53",
      "steps": 4371,
      "worked": "1.93"
    }
  }
}